ihroteka_converter/__init__.py
ihroteka_converter/__main__.py
ihroteka_converter-1.1.2.dist-info/METADATA
ihroteka_converter-1.1.2.dist-info/WHEEL
ihroteka_converter-1.1.2.dist-info/licenses/LICENSE
ihroteka_converter-1.1.2.dist-info/RECORD
