Metadata-Version: 2.4
Name: ihroteka-converter
Version: 1.1.2
Summary: A lightweight package for converting Markdown into Steam-compatible markup.
Project-URL: Homepage, https://github.com/pivoshenko/ihroteka-converter
Project-URL: Repository, https://github.com/pivoshenko/ihroteka-converter
Author-email: Volodymyr Pivoshenko <volodymyr.pivoshenko@gmail.com>
Maintainer-email: Volodymyr Pivoshenko <volodymyr.pivoshenko@gmail.com>
License-Expression: MIT
License-File: LICENSE
Keywords: bbcode,converter,formatter,gaming,ihroteka,markdown,markup,parser,steam,steam-bbcode,steam-bbcode-converter,steam-workshop,text-processing
Classifier: Development Status :: 5 - Production/Stable
Classifier: Environment :: Other Environment
Classifier: Intended Audience :: Developers
Classifier: Intended Audience :: Information Technology
Classifier: License :: OSI Approved :: MIT License
Classifier: Natural Language :: English
Classifier: Operating System :: OS Independent
Classifier: Programming Language :: Python
Classifier: Programming Language :: Python :: 3
Classifier: Programming Language :: Python :: 3.10
Classifier: Programming Language :: Python :: 3.11
Classifier: Programming Language :: Python :: 3.12
Classifier: Programming Language :: Python :: 3.13
Classifier: Topic :: Scientific/Engineering
Classifier: Topic :: Software Development
Classifier: Topic :: Software Development :: Libraries
Classifier: Topic :: Software Development :: Libraries :: Python Modules
Requires-Python: >=3.10
